{
  "catalog_version": "1.0",
  "description": "Content-addressed asset/rig/generator catalog. name@version -> content hash (computed at resolve time via object-hash over the entry's content). Namespaced by kind. Local-first, no service.",
  "entries": {
    "characters": {
      "blip": {
        "id": "blip",
        "version": "1.0.0",
        "kind": "rig",
        "format": "procedural",
        "provider": "blob-creature",
        "uri": "proc://blip",
        "tags": [
          "m2",
          "character",
          "kurzgesagt",
          "flat-vector",
          "ffd"
        ],
        "deps": [],
        "manifest": {
          "mounts": {
            "head_top": {
              "bone": "head"
            },
            "handR": {
              "bone": "armR"
            },
            "handL": {
              "bone": "armL"
            }
          },
          "variants": {
            "palette": [
              "body",
              "bodyDark",
              "ink",
              "belly",
              "accent",
              "white",
              "cheek"
            ]
          },
          "clips": [
            "idle",
            "blink",
            "wave"
          ],
          "bounds": {
            "w": 206,
            "h": 252
          }
        },
        "provenance": {
          "source": "factory",
          "generator": "blob-creature",
          "spec_hash": "d16f4dbeb4c542b404191eb600fa2e538441b8cf",
          "license": "CC0"
        },
        "preview": "characters/blip/blip.preview.png"
      },
      "dragon": {
        "id": "dragon",
        "version": "1.0.0",
        "kind": "rig",
        "format": "dragonbones",
        "provider": "dragonbones",
        "uri": "rig://dragon/dragon.dbones.json",
        "tags": [
          "m1",
          "creature",
          "ffd"
        ],
        "deps": [],
        "manifest": {
          "mounts": {},
          "variants": {}
        },
        "provenance": {
          "source": "pixi-dragonbones-runtime 'starter' demo armature (h1ve2)",
          "license": "MIT"
        }
      },
      "pip": {
        "id": "pip",
        "version": "1.0.0",
        "kind": "rig",
        "format": "procedural",
        "provider": "blob-creature",
        "uri": "proc://pip",
        "tags": [
          "procedural",
          "character",
          "kurzgesagt",
          "factory"
        ],
        "deps": [],
        "manifest": {
          "mounts": {
            "head_top": {
              "bone": "head"
            },
            "handR": {
              "bone": "armR"
            },
            "handL": {
              "bone": "armL"
            }
          },
          "variants": {
            "palette": [
              "body",
              "bodyDark",
              "ink",
              "belly",
              "accent",
              "white",
              "cheek"
            ]
          },
          "clips": [
            "idle",
            "blink",
            "wave"
          ],
          "bounds": {
            "w": 178,
            "h": 260
          }
        },
        "provenance": {
          "source": "factory",
          "generator": "blob-creature",
          "spec_hash": "673028bc93ffb86bd8958cbec1bfa7c00c0c0df4",
          "license": "CC0"
        },
        "preview": "characters/pip/pip.preview.png"
      }
    },
    "props": {
      "gear_prop": {
        "id": "gear_prop",
        "version": "1.0.0",
        "kind": "rig",
        "format": "procedural",
        "provider": "object",
        "uri": "proc://gear_prop",
        "tags": [
          "m2",
          "prop",
          "object",
          "kurzgesagt",
          "flat-vector"
        ],
        "deps": [],
        "manifest": {
          "mounts": {},
          "variants": {
            "variant": []
          }
        },
        "provenance": {
          "source": "factory (core-objects provider — simple flat-vector prop)",
          "license": "CC0"
        }
      }
    },
    "clips": {
      "badge": {
        "id": "badge",
        "version": "1.0.0",
        "kind": "clip",
        "format": "clip",
        "uri": "clip://badge",
        "tags": [
          "m2",
          "clip",
          "nested-composition",
          "precomp"
        ],
        "deps": [],
        "provenance": {
          "source": "factory (M2 nested composition — clip design doc)",
          "license": "CC0"
        }
      },
      "lower-third": {
        "id": "lower-third",
        "version": "1.0.0",
        "kind": "clip",
        "format": "clip",
        "uri": "clip://lower-third",
        "tags": [
          "m2",
          "clip",
          "nested-composition",
          "precomp",
          "lower-third"
        ],
        "deps": [
          "badge@1.0.0"
        ],
        "provenance": {
          "source": "factory (M2 nested composition — clip design doc)",
          "license": "CC0"
        }
      }
    },
    "backgrounds": {
      "bg_gradient": {
        "id": "bg_gradient",
        "version": "1.0.0",
        "kind": "asset",
        "format": "svg",
        "uri": "asset://bg_gradient.svg",
        "tags": [
          "m1",
          "background",
          "parallax"
        ],
        "deps": [],
        "provenance": {
          "source": "authored",
          "license": "CC0"
        }
      },
      "pulse_anim": {
        "id": "pulse_anim",
        "version": "1.0.0",
        "kind": "asset",
        "format": "lottie",
        "uri": "asset://lottie/pulse.lottie.json",
        "tags": [
          "m2",
          "footage",
          "lottie",
          "vector"
        ],
        "deps": [],
        "provenance": {
          "source": "factory (authored minimal Lottie — pulsing ring, deterministic)",
          "license": "CC0"
        }
      },
      "pulse_video": {
        "id": "pulse_video",
        "version": "1.0.0",
        "kind": "asset",
        "format": "video",
        "uri": "asset://video/pulse.webm",
        "tags": [
          "m2",
          "footage",
          "video",
          "alpha"
        ],
        "deps": [],
        "provenance": {
          "source": "factory (deterministic transparent pulse — VP9/yuva420p, frame-exact via OffthreadVideo)",
          "license": "CC0"
        }
      },
      "an32_video": {
        "id": "an32_video",
        "version": "1.0.0",
        "kind": "asset",
        "format": "video",
        "uri": "asset://video/an32.mp4",
        "tags": [
          "footage",
          "video",
          "news"
        ],
        "deps": [],
        "provenance": {
          "source": "x.com/jaggirm/status/2065924227811975441 (IAF An-32 crash, Jorhat, 2026-06-13)",
          "license": "editorial/news"
        }
      }
    },
    "generators": {
      "starfield": {
        "id": "starfield",
        "version": "1.0.0",
        "kind": "generator-preset",
        "format": "generator-preset",
        "uri": "preset://starfield",
        "tags": [
          "generator-preset",
          "scatter",
          "starfield",
          "space",
          "kurzgesagt"
        ],
        "deps": [],
        "provenance": {
          "source": "Kurzgesagt night-sky starfield: many small twinkling star motes on a jittered grid.",
          "generator": "scatter",
          "spec_hash": "025c53530422de775697fa007f836352ea2a3aa9",
          "license": "CC0"
        }
      },
      "dust-motes": {
        "id": "dust-motes",
        "version": "1.0.0",
        "kind": "generator-preset",
        "format": "generator-preset",
        "uri": "preset://dust-motes",
        "tags": [
          "generator-preset",
          "scatter",
          "dust",
          "atmosphere",
          "depth"
        ],
        "deps": [],
        "provenance": {
          "source": "Soft drifting dust motes for warm interior depth: few large translucent blobs slowly wandering.",
          "generator": "scatter",
          "spec_hash": "f5f865530a4189dc38c65a9314b5905f55fac86d",
          "license": "CC0"
        }
      },
      "world-map": {
        "id": "world-map",
        "version": "1.0.0",
        "kind": "generator-preset",
        "format": "generator-preset",
        "uri": "preset://world-map",
        "tags": [
          "generator-preset",
          "map",
          "world",
          "geo"
        ],
        "deps": [],
        "provenance": {
          "source": "World map (110m TopoJSON) for the d3-geo map generator.",
          "generator": "map",
          "spec_hash": "37fdeb76629ca0a9af15f154cd5347b84e1017f1",
          "license": "ODC-PDDL (Natural Earth)"
        }
      },
      "world-in": {
        "id": "world-in",
        "version": "1.0.0",
        "kind": "generator-preset",
        "format": "generator-preset",
        "uri": "preset://world-in",
        "tags": [
          "generator-preset",
          "map",
          "india-official"
        ],
        "deps": [],
        "provenance": {
          "source": "World map, India official boundary (CW).",
          "generator": "map",
          "spec_hash": "efb5e99bd0f67f1bcc864f557915f86d3fb45ae0",
          "license": "ODbL/LGD"
        }
      }
    },
    "kits": {},
    "fonts": {
      "dejavu-sans": {
        "id": "dejavu-sans",
        "version": "1.0.0",
        "kind": "asset",
        "format": "font",
        "uri": "asset://fonts/DejaVuSans.ttf",
        "tags": [
          "font",
          "text",
          "sans",
          "default",
          "vendored-local"
        ],
        "deps": [],
        "provenance": {
          "source": "DejaVu Sans 2.37 (Bitstream Vera derivative) — vendored from /usr/share/fonts/TTF/DejaVuSans.ttf",
          "license": "Bitstream Vera + public-domain (free, permissive)"
        }
      },
      "dejavu-sans-bold": {
        "id": "dejavu-sans-bold",
        "version": "1.0.0",
        "kind": "asset",
        "format": "font",
        "uri": "asset://fonts/DejaVuSans-Bold.ttf",
        "tags": [
          "font",
          "text",
          "sans",
          "bold",
          "vendored-local"
        ],
        "deps": [],
        "provenance": {
          "source": "DejaVu Sans Bold 2.37 (Bitstream Vera derivative) — vendored from /usr/share/fonts/TTF/DejaVuSans-Bold.ttf",
          "license": "Bitstream Vera + public-domain (free, permissive)"
        }
      }
    },
    "stylekits": {
      "kurzgesagt": {
        "id": "kurzgesagt",
        "version": "1.0.0",
        "kind": "stylekit",
        "format": "stylekit",
        "uri": "stylekit://kurzgesagt",
        "tags": [
          "stylekit",
          "kurzgesagt",
          "default",
          "quality-floor"
        ],
        "deps": [],
        "provenance": {
          "source": "factory (relocated from src/render/stylekit.ts — ADR-008 I2)",
          "license": "CC0"
        }
      },
      "plain": {
        "id": "plain",
        "version": "1.0.0",
        "kind": "stylekit",
        "format": "stylekit",
        "uri": "stylekit://plain",
        "tags": [
          "stylekit",
          "plain",
          "flat",
          "technical",
          "floor-off"
        ],
        "deps": [],
        "provenance": {
          "source": "factory (ADR-008 I3 floor opt-out)",
          "license": "CC0"
        }
      },
      "kurzgesagt-nature": {
        "id": "kurzgesagt-nature",
        "version": "1.0.0",
        "kind": "stylekit",
        "format": "stylekit",
        "uri": "stylekit://kurzgesagt-nature",
        "tags": [
          "stylekit",
          "kurzgesagt",
          "nature",
          "paint",
          "painted",
          "atmosphere"
        ],
        "deps": [],
        "provenance": {
          "source": "factory (Painting Style System design 2026-06-23 — paint model DATA)",
          "license": "CC0"
        }
      }
    },
    "palettes": {
      "warm": {
        "id": "warm",
        "version": "1.0.0",
        "kind": "palette",
        "format": "palette",
        "uri": "palette://warm",
        "tags": [
          "palette",
          "color-script",
          "mood",
          "m2"
        ],
        "deps": [],
        "provenance": {
          "source": "factory (color-script §11.4)",
          "license": "CC0"
        }
      },
      "cold": {
        "id": "cold",
        "version": "1.0.0",
        "kind": "palette",
        "format": "palette",
        "uri": "palette://cold",
        "tags": [
          "palette",
          "color-script",
          "mood",
          "m2"
        ],
        "deps": [],
        "provenance": {
          "source": "factory (color-script §11.4)",
          "license": "CC0"
        }
      },
      "hopeful": {
        "id": "hopeful",
        "version": "1.0.0",
        "kind": "palette",
        "format": "palette",
        "uri": "palette://hopeful",
        "tags": [
          "palette",
          "color-script",
          "mood",
          "m2"
        ],
        "deps": [],
        "provenance": {
          "source": "factory (color-script §11.4)",
          "license": "CC0"
        }
      }
    },
    "icons": {
      "icon_heart": {
        "id": "icon_heart",
        "version": "1.0.0",
        "kind": "rig",
        "format": "procedural",
        "provider": "object",
        "uri": "proc://icon_heart",
        "tags": [
          "icon",
          "object",
          "ingested",
          "lucide"
        ],
        "deps": [],
        "manifest": {
          "mounts": {},
          "variants": {
            "variant": []
          }
        },
        "provenance": {
          "source": "lucide@0.469.0 (https://lucide.dev) — icon \"heart\"",
          "spec_hash": "53c939e2231739a3fd61e1ae45f0bb52dbc3230a",
          "license": "ISC"
        }
      },
      "icon_lightbulb": {
        "id": "icon_lightbulb",
        "version": "1.0.0",
        "kind": "rig",
        "format": "procedural",
        "provider": "object",
        "uri": "proc://icon_lightbulb",
        "tags": [
          "icon",
          "object",
          "ingested",
          "lucide"
        ],
        "deps": [],
        "manifest": {
          "mounts": {},
          "variants": {
            "variant": []
          }
        },
        "provenance": {
          "source": "lucide@0.469.0 (https://lucide.dev) — icon \"lightbulb\"",
          "spec_hash": "ecc37affdac11d0ab0e57b183e3afa6846d995d7",
          "license": "ISC"
        }
      },
      "icon_rocket": {
        "id": "icon_rocket",
        "version": "1.0.0",
        "kind": "rig",
        "format": "procedural",
        "provider": "object",
        "uri": "proc://icon_rocket",
        "tags": [
          "icon",
          "object",
          "ingested",
          "lucide"
        ],
        "deps": [],
        "manifest": {
          "mounts": {},
          "variants": {
            "variant": []
          }
        },
        "provenance": {
          "source": "lucide@0.469.0 (https://lucide.dev) — icon \"rocket\"",
          "spec_hash": "e7c6e9f2c6209ae12780ad6966404c6297a379ce",
          "license": "ISC"
        }
      },
      "icon_star": {
        "id": "icon_star",
        "version": "1.0.0",
        "kind": "rig",
        "format": "procedural",
        "provider": "object",
        "uri": "proc://icon_star",
        "tags": [
          "icon",
          "object",
          "ingested",
          "lucide"
        ],
        "deps": [],
        "manifest": {
          "mounts": {},
          "variants": {
            "variant": []
          }
        },
        "provenance": {
          "source": "lucide@0.469.0 (https://lucide.dev) — icon \"star\"",
          "spec_hash": "5d6568e31dcb3bbcc5cbc81381cef41e210cd287",
          "license": "ISC"
        }
      },
      "icon_leaf": {
        "id": "icon_leaf",
        "version": "1.0.0",
        "kind": "rig",
        "format": "procedural",
        "provider": "object",
        "uri": "proc://icon_leaf",
        "tags": [
          "icon",
          "object",
          "ingested",
          "lucide"
        ],
        "deps": [],
        "manifest": {
          "mounts": {},
          "variants": {
            "variant": []
          }
        },
        "provenance": {
          "source": "lucide@0.469.0 (https://lucide.dev) — icon \"leaf\"",
          "spec_hash": "cfe453cfff6ae84436fd1098ee501335b8bde358",
          "license": "ISC"
        }
      },
      "icon_cloud": {
        "id": "icon_cloud",
        "version": "1.0.0",
        "kind": "rig",
        "format": "procedural",
        "provider": "object",
        "uri": "proc://icon_cloud",
        "tags": [
          "icon",
          "object",
          "ingested",
          "lucide"
        ],
        "deps": [],
        "manifest": {
          "mounts": {},
          "variants": {
            "variant": []
          }
        },
        "provenance": {
          "source": "lucide@0.469.0 (https://lucide.dev) — icon \"cloud\"",
          "spec_hash": "ce330e4923dc4d91bbe1563dac97142306df8617",
          "license": "ISC"
        }
      },
      "icon_sun": {
        "id": "icon_sun",
        "version": "1.0.0",
        "kind": "rig",
        "format": "procedural",
        "provider": "object",
        "uri": "proc://icon_sun",
        "tags": [
          "icon",
          "object",
          "ingested",
          "lucide"
        ],
        "deps": [],
        "manifest": {
          "mounts": {},
          "variants": {
            "variant": []
          }
        },
        "provenance": {
          "source": "lucide@0.469.0 (https://lucide.dev) — icon \"sun\"",
          "spec_hash": "39f2c17ac376e5bff8168682390e97db9a02a428",
          "license": "ISC"
        }
      },
      "icon_globe": {
        "id": "icon_globe",
        "version": "1.0.0",
        "kind": "rig",
        "format": "procedural",
        "provider": "object",
        "uri": "proc://icon_globe",
        "tags": [
          "icon",
          "object",
          "ingested",
          "lucide"
        ],
        "deps": [],
        "manifest": {
          "mounts": {},
          "variants": {
            "variant": []
          }
        },
        "provenance": {
          "source": "lucide@0.469.0 (https://lucide.dev) — icon \"globe\"",
          "spec_hash": "b0ae623c600e16af822849da9c9c131d46de37d0",
          "license": "ISC"
        }
      },
      "icon_tree_pine": {
        "id": "icon_tree_pine",
        "version": "1.0.0",
        "kind": "rig",
        "format": "procedural",
        "provider": "object",
        "uri": "proc://icon_tree_pine",
        "tags": [
          "icon",
          "object",
          "ingested",
          "lucide"
        ],
        "deps": [],
        "manifest": {
          "mounts": {},
          "variants": {
            "variant": []
          }
        },
        "provenance": {
          "source": "lucide@0.469.0 (https://lucide.dev) — icon \"tree-pine\"",
          "spec_hash": "b43303b0a89ff6d70be36de68b591e5396a2fefb",
          "license": "ISC"
        }
      },
      "icon_sprout": {
        "id": "icon_sprout",
        "version": "1.0.0",
        "kind": "rig",
        "format": "procedural",
        "provider": "object",
        "uri": "proc://icon_sprout",
        "tags": [
          "icon",
          "object",
          "ingested",
          "lucide"
        ],
        "deps": [],
        "manifest": {
          "mounts": {},
          "variants": {
            "variant": []
          }
        },
        "provenance": {
          "source": "lucide@0.469.0 (https://lucide.dev) — icon \"sprout\"",
          "spec_hash": "0d19db3a7d2e3245bed9a40866e273052a7ff563",
          "license": "ISC"
        }
      }
    },
    "generated": {
      "crystal_prop": {
        "id": "crystal_prop",
        "version": "1.0.0",
        "kind": "asset",
        "format": "image",
        "uri": "asset://generated/crystal_prop.png",
        "tags": [
          "m9",
          "generated",
          "ai",
          "sd-openvino",
          "lcm"
        ],
        "deps": [],
        "provenance": {
          "source": "stable-diffusion-openvino: OpenVINO/LCM_Dreamshaper_v7-fp16-ov (Latent Consistency, SimianLuo)",
          "prompt": "a glowing blue crystal gem, flat vector illustration, simple, centered, white background",
          "seed": 42,
          "model": "lcm",
          "steps": 8,
          "guidance": 1,
          "size": "384x384",
          "cache_hash": "ca829c9a9675eaae",
          "license": "CreativeML-OpenRAIL-M",
          "generated": true
        }
      }
    },
    "footage": {
      "tanker": {
        "id": "tanker",
        "version": "1.0.0",
        "kind": "asset",
        "format": "video",
        "uri": "asset://video/tanker.mp4",
        "tags": [
          "footage",
          "video",
          "pexels",
          "stock"
        ],
        "deps": [],
        "provenance": {
          "source": "Pexels https://www.pexels.com/video/a-boat-is-in-the-water-near-a-large-ship-26329253/ by Thiago  Matos (https://www.pexels.com/@thiagomobile)",
          "prompt": "oil tanker ship ocean",
          "size": "medium",
          "cache_hash": "baa707d073c1",
          "license": "Pexels License (free commercial, no-attribution; credit Pexels + author appreciated)"
        }
      },
      "fuel": {
        "id": "fuel",
        "version": "1.0.0",
        "kind": "asset",
        "format": "video",
        "uri": "asset://video/fuel.mp4",
        "tags": [
          "footage",
          "video",
          "pexels",
          "stock"
        ],
        "deps": [],
        "provenance": {
          "source": "Pexels https://www.pexels.com/video/snowy-night-at-illuminated-gas-station-35560146/ by Luca Dross (https://www.pexels.com/@lucadross) [portrait]",
          "prompt": "gas station fuel pump night",
          "size": "medium",
          "cache_hash": "9262c6383f75",
          "license": "Pexels License (free commercial, no-attribution; credit Pexels + author appreciated)"
        }
      },
      "jet": {
        "id": "jet",
        "version": "1.0.0",
        "kind": "asset",
        "format": "video",
        "uri": "asset://video/jet.mp4",
        "tags": [
          "footage",
          "video",
          "pexels",
          "stock"
        ],
        "deps": [],
        "provenance": {
          "source": "Pexels https://www.pexels.com/video/fighter-jets-in-blue-sky-12954782/ by Rachel Lustiva (https://www.pexels.com/@rachel-lustiva-264852677) [portrait]",
          "prompt": "fighter jet military aircraft sky",
          "size": "medium",
          "cache_hash": "f2ba1edb138b",
          "license": "Pexels License (free commercial, no-attribution; credit Pexels + author appreciated)"
        }
      },
      "fire": {
        "id": "fire",
        "version": "1.0.0",
        "kind": "asset",
        "format": "video",
        "uri": "asset://video/fire.mp4",
        "tags": [
          "footage",
          "video",
          "pexels",
          "stock"
        ],
        "deps": [],
        "provenance": {
          "source": "Pexels https://www.pexels.com/video/vibrant-fireworks-display-exploding-at-night-34588518/ by Pavan Sai .D (https://www.pexels.com/@pavan0307) [portrait]",
          "prompt": "explosion fire night dark",
          "size": "medium",
          "cache_hash": "8d3896613e7e",
          "license": "Pexels License (free commercial, no-attribution; credit Pexels + author appreciated)"
        }
      },
      "warjet": {
        "id": "warjet",
        "version": "1.0.0",
        "kind": "asset",
        "format": "video",
        "uri": "asset://video/warjet.mp4",
        "tags": [
          "footage",
          "video",
          "pexels",
          "stock"
        ],
        "deps": [],
        "provenance": {
          "source": "Pexels https://www.pexels.com/video/fighter-jets-in-blue-sky-12954782/ by Rachel Lustiva (https://www.pexels.com/@rachel-lustiva-264852677) [portrait]",
          "prompt": "military fighter jet flying sky",
          "size": "medium",
          "cache_hash": "1816f2a07c66",
          "license": "Pexels License (free commercial, no-attribution; credit Pexels + author appreciated)"
        }
      },
      "smoke": {
        "id": "smoke",
        "version": "1.0.0",
        "kind": "asset",
        "format": "video",
        "uri": "asset://video/smoke.mp4",
        "tags": [
          "footage",
          "video",
          "pexels",
          "stock"
        ],
        "deps": [],
        "provenance": {
          "source": "Pexels https://www.pexels.com/video/urban-fire-and-smoke-over-city-skyline-37235369/ by Pixel Curator (https://www.pexels.com/@pixelcurator) [portrait]",
          "prompt": "smoke rising war destruction city",
          "size": "medium",
          "cache_hash": "4fd69b68aff6",
          "license": "Pexels License (free commercial, no-attribution; credit Pexels + author appreciated)"
        }
      },
      "oilrig": {
        "id": "oilrig",
        "version": "1.0.0",
        "kind": "asset",
        "format": "video",
        "uri": "asset://video/oilrig.mp4",
        "tags": [
          "footage",
          "video",
          "pexels",
          "stock"
        ],
        "deps": [],
        "provenance": {
          "source": "Pexels https://www.pexels.com/video/industrial-platform-on-sea-11363492/ by Bahruz Z Gachayev (https://www.pexels.com/@bahruz-z-gachayev-163886632) [portrait]",
          "prompt": "offshore oil drilling rig platform ocean",
          "size": "medium",
          "cache_hash": "c85beabaa740",
          "license": "Pexels License (free commercial, no-attribution; credit Pexels + author appreciated)"
        }
      },
      "military": {
        "id": "military",
        "version": "1.0.0",
        "kind": "asset",
        "format": "video",
        "uri": "asset://video/military.mp4",
        "tags": [
          "footage",
          "video",
          "pexels",
          "stock"
        ],
        "deps": [],
        "provenance": {
          "source": "Pexels https://www.pexels.com/video/a-military-vehicle-with-a-machine-gun-on-top-17502682/ by Matthias Groeneveld (https://www.pexels.com/@matthiasgroeneveld) [portrait]",
          "prompt": "military tank armored vehicle convoy",
          "size": "medium",
          "cache_hash": "32a3657e105f",
          "license": "Pexels License (free commercial, no-attribution; credit Pexels + author appreciated)"
        }
      },
      "coastline": {
        "id": "coastline",
        "version": "1.0.0",
        "kind": "asset",
        "format": "video",
        "uri": "asset://video/coastline.mp4",
        "tags": [
          "footage",
          "video",
          "pexels",
          "stock"
        ],
        "deps": [],
        "provenance": {
          "source": "Pexels https://www.pexels.com/video/stunning-aerial-view-of-florida-s-natural-riverscape-34380687/ by Chris  The Island (https://www.pexels.com/@chris-the-island-3570397) [portrait]",
          "prompt": "aerial view river delta tropical coast",
          "size": "medium",
          "cache_hash": "7736cd4f180b",
          "license": "Pexels License (free commercial, no-attribution; credit Pexels + author appreciated)"
        }
      },
      "duqmport": {
        "id": "duqmport",
        "version": "1.0.0",
        "kind": "asset",
        "format": "video",
        "uri": "asset://video/duqmport.mp4",
        "tags": [
          "footage",
          "video",
          "pexels",
          "stock"
        ],
        "deps": [],
        "provenance": {
          "source": "Pexels https://www.pexels.com/video/dynamic-video-of-coastal-shipping-port-and-cranes-34892608/ by Rec Everywhere (https://www.pexels.com/@receverywhere) [portrait]",
          "prompt": "aerial cargo port container terminal cranes",
          "size": "medium",
          "cache_hash": "36f95b5ecacc",
          "license": "Pexels License (free commercial, no-attribution; credit Pexels + author appreciated)"
        }
      },
      "cargoship": {
        "id": "cargoship",
        "version": "1.0.0",
        "kind": "asset",
        "format": "video",
        "uri": "asset://video/cargoship.mp4",
        "tags": [
          "footage",
          "video",
          "pexels",
          "stock"
        ],
        "deps": [],
        "provenance": {
          "source": "Pexels https://www.pexels.com/video/vibrant-port-with-shipping-cranes-at-sunset-34508126/ by Davidsaurik (https://www.pexels.com/@davidsaurik-296473682) [portrait]",
          "prompt": "container ship loaded with cargo containers sea",
          "size": "medium",
          "cache_hash": "2a0f5de08c1c",
          "license": "Pexels License (free commercial, no-attribution; credit Pexels + author appreciated)"
        }
      },
      "warship": {
        "id": "warship",
        "version": "1.0.0",
        "kind": "asset",
        "format": "video",
        "uri": "asset://video/warship.mp4",
        "tags": [
          "footage",
          "video",
          "pexels",
          "stock"
        ],
        "deps": [],
        "provenance": {
          "source": "Pexels https://www.pexels.com/video/indian-coast-guard-vessel-in-sea-patrol-32186197/ by Jomin Thach (https://www.pexels.com/@jomin-thach-428077712) [portrait]",
          "prompt": "navy warship destroyer sea",
          "size": "medium",
          "cache_hash": "c07446a035bd",
          "license": "Pexels License (free commercial, no-attribution; credit Pexels + author appreciated)"
        }
      },
      "himalaya": {
        "id": "himalaya",
        "version": "1.0.0",
        "kind": "asset",
        "format": "video",
        "uri": "asset://video/himalaya.mp4",
        "tags": [
          "footage",
          "video",
          "pexels",
          "stock"
        ],
        "deps": [],
        "provenance": {
          "source": "Pexels https://www.pexels.com/video/scenic-snow-capped-mountain-range-view-35560833/ by Shital Khadgi (https://www.pexels.com/@shital-khadgi-495854046) [portrait]",
          "prompt": "himalaya snow mountain peaks aerial",
          "size": "medium",
          "cache_hash": "5dbc4a248476",
          "license": "Pexels License (free commercial, no-attribution; credit Pexels + author appreciated)"
        }
      },
      "blizzard": {
        "id": "blizzard",
        "version": "1.0.0",
        "kind": "asset",
        "format": "video",
        "uri": "asset://video/blizzard.mp4",
        "tags": [
          "footage",
          "video",
          "pexels",
          "stock"
        ],
        "deps": [],
        "provenance": {
          "source": "Pexels https://www.pexels.com/video/snow-blowing-across-winter-highway-in-ontario-35843229/ by Kim Dodge (https://www.pexels.com/@driver2) [portrait]",
          "prompt": "snow blizzard storm mountain wind",
          "size": "medium",
          "cache_hash": "ba01549deb95",
          "license": "Pexels License (free commercial, no-attribution; credit Pexels + author appreciated)"
        }
      },
      "drone": {
        "id": "drone",
        "version": "1.0.0",
        "kind": "asset",
        "format": "video",
        "uri": "asset://video/drone.mp4",
        "tags": [
          "footage",
          "video",
          "pexels",
          "stock"
        ],
        "deps": [],
        "provenance": {
          "source": "Pexels https://www.pexels.com/video/phantom-4-drone-comming-back-19005328/ by UAVDrone youngman (https://www.pexels.com/@uavdrone-youngman-133608178) [portrait]",
          "prompt": "military drone uav flying sky",
          "size": "medium",
          "cache_hash": "b4b31714c318",
          "license": "Pexels License (free commercial, no-attribution; credit Pexels + author appreciated)"
        }
      },
      "radar": {
        "id": "radar",
        "version": "1.0.0",
        "kind": "asset",
        "format": "video",
        "uri": "asset://video/radar.mp4",
        "tags": [
          "footage",
          "video",
          "pexels",
          "stock"
        ],
        "deps": [],
        "provenance": {
          "source": "Pexels https://www.pexels.com/video/a-large-metal-antenna-in-the-middle-of-a-field-18308551/ by Matthias Groeneveld (https://www.pexels.com/@matthiasgroeneveld) [portrait]",
          "prompt": "radar antenna satellite dish technology",
          "size": "medium",
          "cache_hash": "2832f61bbab0",
          "license": "Pexels License (free commercial, no-attribution; credit Pexels + author appreciated)"
        }
      }
    },
    "photos": {
      "vikrant": {
        "id": "vikrant",
        "version": "1.0.0",
        "kind": "asset",
        "format": "image",
        "uri": "asset://img/vikrant.jpg",
        "tags": [
          "photo",
          "still",
          "wikimedia"
        ],
        "deps": [],
        "provenance": {
          "source": "Wikimedia Commons — \"INS Vikrant being undocked at the Cochin Shipyard Limited in 2015 (04).jpg\" by Indian Navy (GODL-India), https://commons.wikimedia.org/wiki/File:INS_Vikrant_being_undocked_at_the_Cochin_Shipyard_Limited_in_2015_(04).jpg",
          "license": "GODL-India",
          "size": "1000x632",
          "cache_hash": "ce4ade06af70"
        }
      },
      "shipmood": {
        "id": "shipmood",
        "version": "1.0.0",
        "kind": "asset",
        "format": "image",
        "uri": "asset://img/shipmood.jpg",
        "tags": [
          "photo",
          "still",
          "pexels"
        ],
        "deps": [],
        "provenance": {
          "source": "Pexels — photo by Regan Dsouza (https://www.pexels.com/photo/commercial-cargo-ships-on-the-open-sea-36112907/)",
          "license": "Pexels License (free commercial, no-attribution)",
          "size": "6203x4135",
          "cache_hash": "14d01885fceb"
        }
      },
      "soldiers": {
        "id": "soldiers",
        "version": "1.0.0",
        "kind": "asset",
        "format": "image",
        "uri": "asset://img/soldiers.jpg",
        "tags": [
          "photo",
          "still",
          "wikimedia"
        ],
        "deps": [],
        "provenance": {
          "source": "Wikimedia Commons — \"U.S. Army Capt. Mathew Hickey and Indian Army Maj. Sanat Kumar, pause for a photo after reaching the summit of Machoi Peak.jpg\" by U.S. Army (Public domain), https://commons.wikimedia.org/wiki/File:U.S._Army_Capt._Mathew_Hickey_and_Indian_Army_Maj._Sanat_Kumar,_pause_for_a_photo_after_reaching_the_summit_of_Machoi_Peak.jpg",
          "license": "Public domain",
          "size": "1600x1235",
          "cache_hash": "0d7984ad6d38"
        }
      },
      "leh": {
        "id": "leh",
        "version": "1.0.0",
        "kind": "asset",
        "format": "image",
        "uri": "asset://img/leh.jpg",
        "tags": [
          "photo",
          "still",
          "wikimedia"
        ],
        "deps": [],
        "provenance": {
          "source": "Wikimedia Commons — \"PM Modi with officers and soldiers of the Indian Army and Indian Air Force at Leh.jpg\" by Prime Minister's Office, Government of India (GODL-India), https://commons.wikimedia.org/wiki/File:PM_Modi_with_officers_and_soldiers_of_the_Indian_Army_and_Indian_Air_Force_at_Leh.jpg",
          "license": "GODL-India",
          "size": "1600x1209",
          "cache_hash": "fb342c8cac20"
        }
      },
      "rustomuav": {
        "id": "rustomuav",
        "version": "1.0.0",
        "kind": "asset",
        "format": "image",
        "uri": "asset://img/rustomuav.jpg",
        "tags": [
          "photo",
          "still",
          "wikimedia"
        ],
        "deps": [],
        "provenance": {
          "source": "Wikimedia Commons — \"Rustom - 1 UAV.jpg\" by DRDO (GODL-India), https://commons.wikimedia.org/wiki/File:Rustom_-_1_UAV.jpg",
          "license": "GODL-India",
          "size": "350x234",
          "cache_hash": "4e33c467d818"
        }
      }
    },
    "newsshots": {
      "news-tribune": {
        "id": "news-tribune",
        "version": "1.0.0",
        "kind": "asset",
        "format": "image",
        "uri": "asset://img/news-tribune.png",
        "tags": [
          "newsshot",
          "evidence",
          "screenshot"
        ],
        "deps": [],
        "provenance": {
          "source": "The Tribune — https://www.tribuneindia.com/news/india/explainer-india-and-china-troops-disengage-at-disputed-ladakh-border-easing-decades-long-tensions/ (captured 2026-07-08)",
          "license": "editorial / fair-use — brief attributed commentary; publicly-accessible source",
          "cache_hash": "fc71c8ecfbf6"
        }
      },
      "news-orf": {
        "id": "news-orf",
        "version": "1.0.0",
        "kind": "asset",
        "format": "image",
        "uri": "asset://img/news-orf.png",
        "tags": [
          "newsshot",
          "evidence",
          "screenshot"
        ],
        "deps": [],
        "provenance": {
          "source": "orfonline.org — https://www.orfonline.org/expert-speak/india-china-disengagement-progress-on-the-ground-doubts-in-the-air (captured 2026-07-08)",
          "license": "editorial / fair-use — brief attributed commentary; publicly-accessible source",
          "cache_hash": "f707cf659846"
        }
      },
      "news-swarm": {
        "id": "news-swarm",
        "version": "1.0.0",
        "kind": "asset",
        "format": "image",
        "uri": "asset://img/news-swarm.png",
        "tags": [
          "newsshot",
          "evidence",
          "screenshot"
        ],
        "deps": [],
        "provenance": {
          "source": "Organiser — https://organiser.org/2026/05/15/353580/bharat/from-operation-sindoor-to-ai-warfare-how-india-is-building-a-drone-swarm-shield-across-two-fronts/ (captured 2026-07-08)",
          "license": "editorial / fair-use — brief attributed commentary; publicly-accessible source",
          "cache_hash": "33f100a2e712"
        }
      },
      "news-galwan": {
        "id": "news-galwan",
        "version": "1.0.0",
        "kind": "asset",
        "format": "image",
        "uri": "asset://img/news-galwan.png",
        "tags": [
          "newsshot",
          "evidence",
          "screenshot"
        ],
        "deps": [],
        "provenance": {
          "source": "en.wikipedia.org — https://en.wikipedia.org/wiki/2020%E2%80%932021_China%E2%80%93India_skirmishes (captured 2026-07-08)",
          "license": "editorial / fair-use — brief attributed commentary; publicly-accessible source",
          "cache_hash": "dd9b3e9698ae"
        }
      }
    },
    "newsclips": {}
  }
}
